<annotation>
  <folder/>
  <filename>mix_3_top_raw_8.jpg</filename>
  <database/>
  <annotation/>
  <image/>
  <size>
    <height>480</height>
    <width>640</width>
    <depth>3</depth>
  </size>
  <segmented/>
  <object>
    <name>milk_big</name>
    <pose/>
    <truncated/>
    <difficult/>
    <bndbox>
      <xmin>148</xmin>
      <ymin>0</ymin>
      <xmax>193</xmax>
      <ymax>41</ymax>
    </bndbox>
  </object>
  <object>
    <name>book_white</name>
    <pose/>
    <truncated/>
    <difficult/>
    <bndbox>
      <xmin>128</xmin>
      <ymin>52</ymin>
      <xmax>250</xmax>
      <ymax>139</ymax>
    </bndbox>
  </object>
  <object>
    <name>book_yellow</name>
    <pose/>
    <truncated/>
    <difficult/>
    <bndbox>
      <xmin>273</xmin>
      <ymin>13</ymin>
      <xmax>383</xmax>
      <ymax>64</ymax>
    </bndbox>
  </object>
  <object>
    <name>milk_small</name>
    <pose/>
    <truncated/>
    <difficult/>
    <bndbox>
      <xmin>480</xmin>
      <ymin>0</ymin>
      <xmax>527</xmax>
      <ymax>60</ymax>
    </bndbox>
  </object>
  <object>
    <name>marker_blue</name>
    <pose/>
    <truncated/>
    <difficult/>
    <bndbox>
      <xmin>350</xmin>
      <ymin>79</ymin>
      <xmax>410</xmax>
      <ymax>96</ymax>
    </bndbox>
  </object>
  <object>
    <name>bowl</name>
    <pose/>
    <truncated/>
    <difficult/>
    <bndbox>
      <xmin>474</xmin>
      <ymin>94</ymin>
      <xmax>531</xmax>
      <ymax>138</ymax>
    </bndbox>
  </object>
  <object>
    <name>can_coke</name>
    <pose/>
    <truncated/>
    <difficult/>
    <bndbox>
      <xmin>436</xmin>
      <ymin>157</ymin>
      <xmax>483</xmax>
      <ymax>225</ymax>
    </bndbox>
  </object>
  <object>
    <name>stapler</name>
    <pose/>
    <truncated/>
    <difficult/>
    <bndbox>
      <xmin>309</xmin>
      <ymin>134</ymin>
      <xmax>332</xmax>
      <ymax>193</ymax>
    </bndbox>
  </object>
  <object>
    <name>pen_black</name>
    <pose/>
    <truncated/>
    <difficult/>
    <bndbox>
      <xmin>216</xmin>
      <ymin>137</ymin>
      <xmax>261</xmax>
      <ymax>174</ymax>
    </bndbox>
  </object>
  <object>
    <name>marker_red</name>
    <pose/>
    <truncated/>
    <difficult/>
    <bndbox>
      <xmin>304</xmin>
      <ymin>203</ymin>
      <xmax>363</xmax>
      <ymax>251</ymax>
    </bndbox>
  </object>
  <object>
    <name>can_pepsi</name>
    <pose/>
    <truncated/>
    <difficult/>
    <bndbox>
      <xmin>70</xmin>
      <ymin>139</ymin>
      <xmax>119</xmax>
      <ymax>205</ymax>
    </bndbox>
  </object>
  <object>
    <name>bowl</name>
    <pose/>
    <truncated/>
    <difficult/>
    <bndbox>
      <xmin>156</xmin>
      <ymin>243</ymin>
      <xmax>245</xmax>
      <ymax>323</ymax>
    </bndbox>
  </object>
  <object>
    <name>book_blue</name>
    <pose/>
    <truncated/>
    <difficult/>
    <bndbox>
      <xmin>611</xmin>
      <ymin>193</ymin>
      <xmax>640</xmax>
      <ymax>275</ymax>
    </bndbox>
  </object>
</annotation>
